kim_query/__init__.py
kim_query/_version.py
kim_query/kim_query.py
kim_query-4.0.0.dist-info/LICENSE.CDDL
kim_query-4.0.0.dist-info/METADATA
kim_query-4.0.0.dist-info/WHEEL
kim_query-4.0.0.dist-info/top_level.txt
kim_query-4.0.0.dist-info/RECORD
