Metadata-Version: 2.2
Name: kim-query
Version: 4.0.0
Summary: Helper routines for querying the OpenKIM Repository
Author-email: "Daniel S. Karls" <karl0100umn@gmail.com>, ilia Nikiforov <nikif002@umn.edu>, Claire Waters <bwaters@umn.edu>
Maintainer-email: ilia Nikiforov <nikif002@umn.edu>, Claire Waters <bwaters@umn.edu>, "Daniel S. Karls" <karl0100umn@gmail.com>
Project-URL: Homepage, https://github.com/openkim/kim-query
Project-URL: Issues, https://github.com/openkim/kim-query/issues
Keywords: kim-query,kim_query,openkim
Classifier: Development Status :: 5 - Production/Stable
Classifier: License :: OSI Approved :: Common Development and Distribution License 1.0 (CDDL-1.0)
Classifier: Programming Language :: Python :: 3
Classifier: Operating System :: OS Independent
Classifier: Topic :: Scientific/Engineering
Classifier: Intended Audience :: Science/Research
Requires-Python: >=3.6
License-File: LICENSE.CDDL
Requires-Dist: requests
